cipherer/__init__.py
cipherer/adfgx.py
cipherer/affine.py
cipherer/bacon.py
cipherer/caeser_cipher.py
cipherer/greek_square.py
cipherer/rail_fence_cipher.py
cipherer-0.0.3.dist-info/METADATA
cipherer-0.0.3.dist-info/WHEEL
cipherer-0.0.3.dist-info/top_level.txt
cipherer-0.0.3.dist-info/RECORD
