Metadata-Version: 2.1
Name: cipherer
Version: 0.0.3
Summary: A package with 5 simple ciphers
Author: Vikram Fox and Jacob Friedman
Author-email: vikramsfox@gmail.com
Keywords: python,cipher,encryption,decryption
Classifier: Development Status :: 3 - Alpha
Classifier: Intended Audience :: Education
Classifier: Programming Language :: Python :: 3
Classifier: Operating System :: MacOS :: MacOS X
Classifier: Operating System :: Microsoft :: Windows
